mcp_notify/__init__.py
mcp_notify/__main__.py
mcp_notify/hass.py
mcp_notify/other.py
mcp_notify/tgbot.py
mcp_notify/util.py
mcp_notify/wework.py
mcp_notify-0.1.9.dist-info/METADATA
mcp_notify-0.1.9.dist-info/WHEEL
mcp_notify-0.1.9.dist-info/entry_points.txt
mcp_notify-0.1.9.dist-info/licenses/LICENSE
mcp_notify-0.1.9.dist-info/RECORD
