Metadata-Version: 2.4
Name: mcp-notify
Version: 0.1.9
Summary: MCP Server for notify
Project-URL: Repository, https://github.com/aahl/mcp-notify
License: MIT
License-File: LICENSE
Keywords: lark,llm,mcp,notify,ntfy,telegram,weixin,wework
Requires-Python: >=3.10
Requires-Dist: cachetools>=6.2.0
Requires-Dist: fastmcp>=2.0.0
Requires-Dist: python-telegram-bot>=22.0
Requires-Dist: telegramify-markdown>=0.5
Requires-Dist: telegramify-markdown[mermaid]>=0.5
